{
    "version": 8,
    "configurePresets": [
        {
            "name": "test",
            "displayName": "GCC 14.2.0 x86_64-w64-mingw32 (ucrt64)",
            "description": "Using compilers: C = C:/Software/MSYS2/ucrt64/bin/gcc.exe, CXX = C:/Software/MSYS2/ucrt64/bin/g++.exe",
            "generator": "Unix Makefiles",
            "binaryDir": "${sourceDir}/out/build/${presetName}",
            "cacheVariables": {
                "CMAKE_INSTALL_PREFIX": "${sourceDir}/out/install/${presetName}",
                "CMAKE_C_COMPILER": "C:/Software/MSYS2/ucrt64/bin/gcc.exe",
                "CMAKE_CXX_COMPILER": "C:/Software/MSYS2/ucrt64/bin/g++.exe",
                "CMAKE_BUILD_TYPE": "Debug"
            }
        }
    ]
}